parse_binary_file/__init__.py
parse_binary_file/_version.py
parse_binary_file/data.py
parse_binary_file/data_types.py
parse_binary_file/errors.py
parse_binary_file/field.py
parse_binary_file/field_description.py
parse_binary_file/file_format.py
parse_binary_file/helpers.py
parse_binary_file/parser.py
parse_binary_file/test_field.py
parse_binary_file/test_field_description.py
parse_binary_file/test_file_format.py
parse_binary_file/test_parser.py
parse_binary_file-0.0.2.dist-info/LICENSE
parse_binary_file-0.0.2.dist-info/METADATA
parse_binary_file-0.0.2.dist-info/WHEEL
parse_binary_file-0.0.2.dist-info/top_level.txt
parse_binary_file-0.0.2.dist-info/RECORD
