Metadata-Version: 2.1
Name: parse_binary_file
Version: 0.0.2
Summary: Parse binary files by describing their structure.
Home-page: https://github.com/bicarlsen/parse_binary_file.git
Author: Brian Carlsen
Author-email: carlsen.bri@gmail.com
License: UNKNOWN
Keywords: parse,binary,file
Platform: UNKNOWN
Classifier: Programming Language :: Python :: 3
Classifier: License :: OSI Approved :: MIT License
Classifier: Operating System :: OS Independent
License-File: LICENSE
